ocelli/__init__.py
ocelli/pl.py
ocelli/pp.py
ocelli/tl.py
ocelli/forceatlas2/forceatlas2.jar
ocelli/forceatlas2/gephi-toolkit-0.9.2-all.jar
ocelli/plotting/__init__.py
ocelli/plotting/bar.py
ocelli/plotting/projections.py
ocelli/plotting/scatter.py
ocelli/plotting/scatter_interactive.py
ocelli/plotting/violin.py
ocelli/preprocessing/LDA.py
ocelli/preprocessing/__init__.py
ocelli/preprocessing/modality_generation.py
ocelli/preprocessing/neighbors.py
ocelli/tools/FA2.py
ocelli/tools/MDM.py
ocelli/tools/UMAP.py
ocelli/tools/__init__.py
ocelli/tools/imputation.py
ocelli/tools/louvain.py
ocelli/tools/mean_z_scores.py
ocelli/tools/neighbors_graph.py
ocelli/tools/projection.py
ocelli/tools/scale_weights.py
ocelli/tools/transitions_graph.py
ocelli/tools/weights.py
ocelli-0.1.1.dist-info/METADATA
ocelli-0.1.1.dist-info/WHEEL
ocelli-0.1.1.dist-info/top_level.txt
ocelli-0.1.1.dist-info/RECORD
