Metadata-Version: 2.1
Name: ocelli
Version: 0.1.1
Summary: Single-cell developmental landscapes from multimodal data
Home-page: https://github.com/TabakaLab/ocelli
Author: Piotr Rutkowski
Author-email: prutkowski@ichf.edu.pl
License: BSD-Clause 2
Download-URL: https://github.com/TabakaLab/ocelli
Keywords: single cell,developmental process,multimodal,multiomics
Platform: UNKNOWN
Classifier: License :: OSI Approved :: BSD License
Classifier: Intended Audience :: Science/Research
Classifier: Natural Language :: English
Classifier: Programming Language :: Python :: 3
Classifier: Programming Language :: Python :: 3.7
Classifier: Programming Language :: Python :: 3.8
Classifier: Programming Language :: Python :: 3.9
Classifier: Programming Language :: Python :: 3.10
Classifier: Programming Language :: Python :: 3.11
Classifier: Programming Language :: Python :: 3.12
Classifier: Topic :: Scientific/Engineering :: Bio-Informatics
Classifier: Topic :: Scientific/Engineering :: Visualization
Requires-Python: >=3.7
Requires-Dist: anndata
Requires-Dist: matplotlib
Requires-Dist: numpy
Requires-Dist: pandas
Requires-Dist: plotly
Requires-Dist: ray
Requires-Dist: scikit-learn
Requires-Dist: scipy
Requires-Dist: statsmodels
Requires-Dist: umap-learn
Requires-Dist: scanpy
Requires-Dist: louvain
